nztests/__init__.py
nztests/__version__.py
nztests/tempfile.py
nztests-1b0.dev1.data/data/requirements.txt
nztests-1b0.dev1.dist-info/METADATA
nztests-1b0.dev1.dist-info/WHEEL
nztests-1b0.dev1.dist-info/entry_points.txt
nztests-1b0.dev1.dist-info/top_level.txt
nztests-1b0.dev1.dist-info/RECORD
