Metadata-Version: 2.1
Name: nztests
Version: 1b0.dev1
Summary: Tools for tests
Home-page: UNKNOWN
Author: Clement
Author-email: neze+pypi@melix.org
License: UNKNOWN
Platform: UNKNOWN
Classifier: Programming Language :: Python :: 3
Requires-Dist: pathlib2
